ocsw/__init__.py
ocsw/cli.py
ocsw/client.py
ocsw/constants.py
ocsw/errors.py
ocsw/sync2async.py
ocsw/version.py
ocsw/.vscode/.ropeproject/config.py
ocsw/api/__init__.py
ocsw/api/action.py
ocsw/api/blueprint.py
ocsw/api/client.py
ocsw/api/company.py
ocsw/api/connector.py
ocsw/api/device.py
ocsw/api/event.py
ocsw/api/firmware.py
ocsw/api/group.py
ocsw/api/identity.py
ocsw/api/local_action.py
ocsw/api/release.py
ocsw/api/stream.py
ocsw/cmd/__init__.py
ocsw/cmd/cmd_blueprint.py
ocsw/cmd/cmd_cloud.py
ocsw/cmd/cmd_cloud_action.py
ocsw/cmd/cmd_cloud_connector.py
ocsw/cmd/cmd_company.py
ocsw/cmd/cmd_device.py
ocsw/cmd/cmd_edge_action.py
ocsw/cmd/cmd_firmware.py
ocsw/cmd/cmd_group.py
ocsw/cmd/cmd_identity.py
ocsw/cmd/cmd_login.py
ocsw/cmd/cmd_logout.py
ocsw/cmd/cmd_release.py
ocsw/cmd/cmd_stream.py
ocsw/cmd/cmd_user.py
ocsw/cmd/diagram.py
ocsw/models/__init__.py
ocsw/models/actions.py
ocsw/models/blueprints.py
ocsw/models/companies.py
ocsw/models/resource.py
ocsw/utils/__init__.py
ocsw/utils/argparse_action.py
ocsw/utils/color_diff.py
ocsw/utils/config.py
ocsw/utils/date_fns.py
ocsw/utils/format_date.py
ocsw/utils/format_pretty_json.py
ocsw/utils/format_size.py
ocsw/utils/helpers.py
ocsw/utils/query_params.py
ocsw/utils/render.py
ocsw/utils/secrets.py
ocsw/utils/table.py
ocsw/utils/tmd.py
ocsw-0.3.0.dist-info/LICENSE
ocsw-0.3.0.dist-info/METADATA
ocsw-0.3.0.dist-info/WHEEL
ocsw-0.3.0.dist-info/entry_points.txt
ocsw-0.3.0.dist-info/top_level.txt
ocsw-0.3.0.dist-info/zip-safe
ocsw-0.3.0.dist-info/RECORD
