Metadata-Version: 2.1
Name: ocsw
Version: 0.3.0
Summary: Octave Cloud IoT Command Line Interface (CLI)
Home-page: https://github.com/maxim-s-barabash/ocsw
Author: Barabash Maxim
Author-email: maxim.s.barabash@gmail.com
Maintainer: Barabash Maxim
Maintainer-email: maxim.s.barabash@gmail.com
License: MIT License
Project-URL: Source, https://github.com/maxim-s-barabash/ocsw
Project-URL: Tracker, https://github.com/maxim-s-barabash/ocsw/issues
Keywords: IoT,octave,cloud,cli
Platform: Independent
Classifier: Development Status :: 3 - Alpha
Classifier: Intended Audience :: Developers
Classifier: License :: OSI Approved :: MIT License
Classifier: Natural Language :: English
Classifier: Operating System :: OS Independent
Classifier: Programming Language :: Python
Classifier: Programming Language :: Python :: 3.6
Classifier: Programming Language :: Python :: 3.7
Classifier: Programming Language :: Python :: 3.8
Classifier: Topic :: Software Development :: Libraries :: Python Modules
Classifier: Topic :: Software Development
Classifier: Topic :: Utilities
Requires-Python: >=3.6
Requires-Dist: aiohttp
Requires-Dist: PyYAML
Requires-Dist: colorama
